README.rst
setup.py
palmer/__init__.py
palmer/app.py
palmer/authentications.py
palmer/compat.py
palmer/config.py
palmer/exceptions.py
palmer/permissions.py
palmer/renderers.py
palmer/request.py
palmer/response.py
palmer/session.py
palmer/views.py
palmer.egg-info/PKG-INFO
palmer.egg-info/SOURCES.txt
palmer.egg-info/dependency_links.txt
palmer.egg-info/requires.txt
palmer.egg-info/top_level.txt
palmer/__pycache__/__init__.cpython-35.pyc
palmer/__pycache__/app.cpython-35.pyc
palmer/__pycache__/compat.cpython-35.pyc
palmer/__pycache__/config.cpython-35.pyc
palmer/__pycache__/exceptions.cpython-35.pyc
palmer/__pycache__/renderers.cpython-35.pyc
palmer/__pycache__/request.cpython-35.pyc
palmer/__pycache__/response.cpython-35.pyc
palmer/__pycache__/session.cpython-35.pyc
palmer/utils/__init__.py
palmer/utils/http_statuses.py
palmer/utils/swagger.py
palmer/utils/translation.py
palmer/utils/__pycache__/__init__.cpython-35.pyc
palmer/utils/__pycache__/http_statuses.cpython-35.pyc
palmer/utils/__pycache__/translation.cpython-35.pyc